beaker_gantry-3.4.6.dist-info/licenses/LICENSE
gantry/__init__.py
gantry/__main__.py
gantry/aliases.py
gantry/all_reduce_bench.py
gantry/api.py
gantry/beaker_utils.py
gantry/config.py
gantry/constants.py
gantry/entrypoint.sh
gantry/exceptions.py
gantry/git_utils.py
gantry/launch.py
gantry/py.typed
gantry/recipe.py
gantry/utils.py
gantry/version.py
gantry/callbacks/__init__.py
gantry/callbacks/callback.py
gantry/callbacks/slack.py
gantry/commands/__init__.py
gantry/commands/completion.py
gantry/commands/config.py
gantry/commands/find_gpus.py
gantry/commands/follow.py
gantry/commands/list.py
gantry/commands/logs.py
gantry/commands/main.py
gantry/commands/open.py
gantry/commands/run.py
gantry/commands/stop.py
beaker_gantry-3.4.6.dist-info/METADATA
beaker_gantry-3.4.6.dist-info/WHEEL
beaker_gantry-3.4.6.dist-info/entry_points.txt
beaker_gantry-3.4.6.dist-info/top_level.txt
beaker_gantry-3.4.6.dist-info/RECORD
