Metadata-Version: 2.4
Name: beaker-gantry
Version: 3.4.6
Summary: Gantry streamlines running Python experiments in Beaker by managing containers and boilerplate for you
Author-email: Allen Institute for Artificial Intelligence <contact@allenai.org>, Pete Walsh <petew@allenai.org>
Project-URL: homepage, https://github.com/allenai/beaker-gantry
Project-URL: repository, https://github.com/allenai/beaker-gantry
Classifier: Intended Audience :: Science/Research
Classifier: Programming Language :: Python :: 3
Classifier: Topic :: Scientific/Engineering :: Artificial Intelligence
Requires-Python: >=3.10
License-File: LICENSE
Requires-Dist: beaker-py<3.0,>=2.5.1
Requires-Dist: GitPython<4.0,>=3.0
Requires-Dist: rich
Requires-Dist: click
Requires-Dist: click-help-colors
Requires-Dist: click-option-group
Requires-Dist: petname<3.0,>=2.6
Requires-Dist: requests
Requires-Dist: packaging
Requires-Dist: tomli
Requires-Dist: dataclass-extensions
Requires-Dist: PyYAML
Provides-Extra: dev
Requires-Dist: ruff; extra == "dev"
Requires-Dist: mypy<2.0,>=1.19.1; extra == "dev"
Requires-Dist: types-requests; extra == "dev"
Requires-Dist: types-protobuf; extra == "dev"
Requires-Dist: types-PyYAML; extra == "dev"
Requires-Dist: black<24.0,>=23.0; extra == "dev"
Requires-Dist: isort<5.13,>=5.11; extra == "dev"
Requires-Dist: pytest; extra == "dev"
Requires-Dist: twine>=1.11.0; extra == "dev"
Requires-Dist: build; extra == "dev"
Requires-Dist: setuptools; extra == "dev"
Requires-Dist: wheel; extra == "dev"
Dynamic: license-file
